README.rst
setup.py
spotify_ripper/__init__.py
spotify_ripper/color_lines.py
spotify_ripper/eventloop.py
spotify_ripper/main.py
spotify_ripper/post_actions.py
spotify_ripper/progress.py
spotify_ripper/ripper.py
spotify_ripper/sync.py
spotify_ripper/tags.py
spotify_ripper/utils.py
spotify_ripper/web.py
spotify_ripper_morgaroth.egg-info/PKG-INFO
spotify_ripper_morgaroth.egg-info/SOURCES.txt
spotify_ripper_morgaroth.egg-info/dependency_links.txt
spotify_ripper_morgaroth.egg-info/entry_points.txt
spotify_ripper_morgaroth.egg-info/not-zip-safe
spotify_ripper_morgaroth.egg-info/requires.txt
spotify_ripper_morgaroth.egg-info/top_level.txt