Metadata-Version: 1.1
Name: spotify-ripper-morgaroth
Version: 2.9.2
Summary: a small ripper for Spotify that rips Spotify URIs to audio files
Home-page: https://github.com/morgaroth/spotify-ripper
Author: Mateusz Jaje
Author-email: mateuszjaje@gmail.com
License: MIT
Download-URL: https://github.com/morgaroth/spotify-ripper-morgaroth/tarball/2.9.2
Keywords: spotify ripper mp3 ogg vorbis flac opus acc mp4 m4a
Platform: UNKNOWN
Classifier: Topic :: Multimedia :: Sound/Audio
Classifier: Topic :: Multimedia :: Sound/Audio :: Capture/Recording
Classifier: License :: OSI Approved :: MIT License
Classifier: Environment :: Console
Classifier: Intended Audience :: Developers
Classifier: Programming Language :: Python :: 2
Classifier: Programming Language :: Python :: 2.7
Classifier: Programming Language :: Python :: 3
Classifier: Programming Language :: Python :: 3.4
